main.py
advanced_features/__init__.py
advanced_features/active_learning_sampler.py
toolkit/__init__.py
toolkit/data_handler.py
toolkit/labeling.py
toolkit/training.py
toolkit/utils.py
yolo_dataset_studio-0.1.0.dist-info/licenses/LICENSE
yolo_dataset_studio-0.1.0.dist-info/METADATA
yolo_dataset_studio-0.1.0.dist-info/WHEEL
yolo_dataset_studio-0.1.0.dist-info/entry_points.txt
yolo_dataset_studio-0.1.0.dist-info/top_level.txt
yolo_dataset_studio-0.1.0.dist-info/RECORD
