Metadata-Version: 2.4
Name: yolo-dataset-studio
Version: 0.1.0
Summary: Integrated CLI pipeline for creating custom YOLO datasets with optional ROS 2 bag ingestion.
Author: kdh10086
License: MIT License
Project-URL: Homepage, https://github.com/kdh10086/YOLO_Dataset_Studio
Project-URL: Issue Tracker, https://github.com/kdh10086/YOLO_Dataset_Studio/issues
Classifier: License :: OSI Approved :: MIT License
Classifier: Programming Language :: Python
Classifier: Programming Language :: Python :: 3
Classifier: Programming Language :: Python :: 3.10
Classifier: Programming Language :: Python :: 3.11
Classifier: Programming Language :: Python :: 3.12
Classifier: Operating System :: OS Independent
Classifier: Topic :: Scientific/Engineering :: Artificial Intelligence
Requires-Python: >=3.10
License-File: LICENSE
Requires-Dist: ultralytics
Requires-Dist: torch
Requires-Dist: torchvision
Requires-Dist: opencv-python
Requires-Dist: numpy
Requires-Dist: pyyaml
Requires-Dist: tqdm
Requires-Dist: Pillow
Requires-Dist: scikit-learn
Requires-Dist: transformers
Requires-Dist: matplotlib
Provides-Extra: ros2bag
Requires-Dist: rclpy; extra == "ros2bag"
Requires-Dist: rosbag2_py; extra == "ros2bag"
Requires-Dist: rosidl_runtime_py; extra == "ros2bag"
Requires-Dist: rosbag2_interfaces; extra == "ros2bag"
Requires-Dist: cv_bridge; extra == "ros2bag"
Requires-Dist: sensor-msgs; extra == "ros2bag"
Provides-Extra: dev
Requires-Dist: pytest; extra == "dev"
Dynamic: license-file
